redis_cli/__init__.py
redis_cli/client.py
redis_cli/utils.py
redis_cli-1.0.1.dist-info/LICENSE
redis_cli-1.0.1.dist-info/METADATA
redis_cli-1.0.1.dist-info/WHEEL
redis_cli-1.0.1.dist-info/top_level.txt
redis_cli-1.0.1.dist-info/RECORD
