Metadata-Version: 2.1
Name: redis-cli
Version: 1.0.1
Summary: A Redis Python Client
Author-email: William Wang <williamw0825@gmail.com>
Project-URL: Homepage, https://github.com/will4j/redis-cli-py
Project-URL: Bug Tracker, https://github.com/will4j/redis-cli-py/issues
Keywords: Redis,Python,client
Classifier: Programming Language :: Python :: 3
Classifier: License :: OSI Approved :: MIT License
Classifier: Operating System :: OS Independent
Requires-Python: >=3.7
License-File: LICENSE
Requires-Dist: redis>=4
